nicolas/__init__.py
nicolas/_version.py
nicolas/cache.py
nicolas/cli.py
nicolas/memory.py
nicolas/redis.py
nicolas/sentinel.py
nicolas_cache-25.8.18.dist-info/licenses/AUTHORS.rst
nicolas_cache-25.8.18.dist-info/licenses/LICENSE
nicolas_cache-25.8.18.dist-info/METADATA
nicolas_cache-25.8.18.dist-info/WHEEL
nicolas_cache-25.8.18.dist-info/top_level.txt
nicolas_cache-25.8.18.dist-info/RECORD
