Metadata-Version: 2.4
Name: nicolas-cache
Version: 25.8.18
Summary: Python Caching library with tagging support
Author-email: Yves Thommes <hello@wickeddoc.com>
Maintainer-email: Yves Thommes <hello@wickeddoc.com>
License: Unlicense
Project-URL: bugs, https://github.com/wickeddoc/nicolas-cache/issues
Project-URL: changelog, https://github.com/wickeddoc/nicolas-cache/blob/master/changelog.md
Project-URL: homepage, https://github.com/wickeddoc/nicolas-cache
License-File: LICENSE
License-File: AUTHORS.rst
Requires-Dist: redis
Requires-Dist: typer
Provides-Extra: dev
Requires-Dist: coverage; extra == "dev"
Requires-Dist: mypy; extra == "dev"
Requires-Dist: pytest; extra == "dev"
Requires-Dist: ruff; extra == "dev"
Requires-Dist: setuptools-scm; extra == "dev"
Requires-Dist: build; extra == "dev"
Requires-Dist: twine; extra == "dev"
Dynamic: license-file
